jprq/__init__.py
jprq/http.py
jprq/main.py
jprq/tunnel.py
jprq-1.0.4.dist-info/METADATA
jprq-1.0.4.dist-info/WHEEL
jprq-1.0.4.dist-info/entry_points.txt
jprq-1.0.4.dist-info/top_level.txt
jprq-1.0.4.dist-info/RECORD
